dbt_prql/patch.py
zzz_dbt_prql.pth
dbt_prql-0.2.3.dist-info/LICENSE
dbt_prql-0.2.3.dist-info/WHEEL
dbt_prql-0.2.3.dist-info/METADATA
dbt_prql-0.2.3.dist-info/RECORD
