Metadata-Version: 2.1
Name: dbt-prql
Version: 0.2.3
Summary: Write PRQL in dbt models
Home-page: https://github.com/prql/dbt-prql
License: Apache-2.0
Author: Maximilian Roos
Author-email: m@maxroos.com
Requires-Python: >=3.7.3
Classifier: License :: OSI Approved :: Apache Software License
Classifier: Programming Language :: Python :: 3
Classifier: Programming Language :: Python :: 3.10
Classifier: Programming Language :: Python :: 3.8
Classifier: Programming Language :: Python :: 3.9
Requires-Dist: dbt-core (>=1.1.0,<1.3.0)
Requires-Dist: prql_python (>=0.2.0)
Project-URL: Repository, https://github.com/prql/dbt-prql
